adafruit_spa06_003.py
adafruit_circuitpython_spa06_003-1.1.0.dist-info/licenses/LICENSE
adafruit_circuitpython_spa06_003-1.1.0.dist-info/METADATA
adafruit_circuitpython_spa06_003-1.1.0.dist-info/WHEEL
adafruit_circuitpython_spa06_003-1.1.0.dist-info/top_level.txt
adafruit_circuitpython_spa06_003-1.1.0.dist-info/RECORD
