Metadata-Version: 2.4
Name: adafruit-circuitpython-spa06-003
Version: 1.1.0
Summary: CircuitPython driver for SPA06-003 temperature and pressure sensor breakout.
Author-email: Adafruit Industries <circuitpython@adafruit.com>
License: MIT
Project-URL: Homepage, https://github.com/adafruit/Adafruit_CircuitPython_SPA06_003
Keywords: adafruit,blinka,circuitpython,micropython,spa06_003,temperature,temp,pressure,hPa,sensor
Classifier: Intended Audience :: Developers
Classifier: Topic :: Software Development :: Libraries
Classifier: Topic :: Software Development :: Embedded Systems
Classifier: Topic :: System :: Hardware
Classifier: License :: OSI Approved :: MIT License
Classifier: Programming Language :: Python :: 3
License-File: LICENSE
Requires-Dist: Adafruit-Blinka
Requires-Dist: adafruit-circuitpython-busdevice
Requires-Dist: adafruit-circuitpython-register
Provides-Extra: optional
Dynamic: license-file
